html2ans/__init__.py
html2ans/base.py
html2ans/default.py
html2ans/exc.py
html2ans/parsers/__init__.py
html2ans/parsers/audio.py
html2ans/parsers/base.py
html2ans/parsers/embeds.py
html2ans/parsers/image.py
html2ans/parsers/raw_html.py
html2ans/parsers/text.py
html2ans/parsers/utils.py
html2ans-3.0.6.dist-info/LICENSE
html2ans-3.0.6.dist-info/METADATA
html2ans-3.0.6.dist-info/WHEEL
html2ans-3.0.6.dist-info/top_level.txt
html2ans-3.0.6.dist-info/RECORD
