Metadata-Version: 2.1
Name: html2ans
Version: 3.0.6
Summary: Convert HTML to ANS
Home-page: https://github.com/washingtonpost/html2ans
Author: Arc Professional Services Team
Author-email: arc.professional.services@gmail.com
License: MIT
Platform: UNKNOWN
Classifier: Intended Audience :: Developers
Classifier: License :: OSI Approved :: MIT License
Classifier: Programming Language :: Python
Classifier: Programming Language :: Python :: 2
Classifier: Programming Language :: Python :: 2.7
Classifier: Programming Language :: Python :: 3
Classifier: Programming Language :: Python :: 3.5
Classifier: Programming Language :: Python :: 3.6
Classifier: Programming Language :: Python :: 3.7
Requires-Dist: BeautifulSoup4 (<5)
Requires-Dist: html5lib (<2)
Requires-Dist: lxml (<5)
Requires-Dist: six (<2)
Requires-Dist: furl (<3,>=2.0.0)
Requires-Dist: ftfy (<5) ; python_version < "3"
Requires-Dist: ftfy (<6) ; python_version >= "3"
Provides-Extra: dev
Requires-Dist: sphinx ; extra == 'dev'
Requires-Dist: pytest (<5) ; extra == 'dev'
Provides-Extra: tests
Requires-Dist: pytest (<5) ; extra == 'tests'
